kattis2canvas/__init__.py
kattis2canvas/__main__.py
kattis2canvas/cli.py
kattis2canvas-0.1.7.dist-info/METADATA
kattis2canvas-0.1.7.dist-info/WHEEL
kattis2canvas-0.1.7.dist-info/entry_points.txt
kattis2canvas-0.1.7.dist-info/top_level.txt
kattis2canvas-0.1.7.dist-info/RECORD
