Metadata-Version: 2.4
Name: kattis2canvas
Version: 0.1.7
Summary: CLI tool to integrate Kattis offerings with Canvas LMS courses
Author: bcr33d
License-Expression: MIT
Project-URL: Homepage, https://github.com/bcr33d/kattis2canvas
Project-URL: Repository, https://github.com/bcr33d/kattis2canvas
Keywords: kattis,canvas,lms,education,grading
Classifier: Development Status :: 4 - Beta
Classifier: Environment :: Console
Classifier: Intended Audience :: Education
Classifier: Operating System :: OS Independent
Classifier: Programming Language :: Python :: 3
Classifier: Programming Language :: Python :: 3.8
Classifier: Programming Language :: Python :: 3.9
Classifier: Programming Language :: Python :: 3.10
Classifier: Programming Language :: Python :: 3.11
Classifier: Programming Language :: Python :: 3.12
Classifier: Topic :: Education
Requires-Python: >=3.8
Requires-Dist: click>=8.0
Requires-Dist: requests>=2.25
Requires-Dist: beautifulsoup4>=4.9
Requires-Dist: canvasapi>=2.0
Requires-Dist: python-dateutil>=2.8
